validators_rs/__init__.py
validators_rs/validators_rs.cpython-39-darwin.so
validators_rs-0.1.1.dist-info/METADATA
validators_rs-0.1.1.dist-info/WHEEL
validators_rs-0.1.1.dist-info/RECORD
