Metadata-Version: 2.4
Name: validators_rs
Version: 0.1.1
Classifier: Development Status :: 4 - Beta
Classifier: Intended Audience :: Developers
Classifier: License :: OSI Approved :: MIT License
Classifier: Programming Language :: Python :: 3
Classifier: Programming Language :: Python :: 3.8
Classifier: Programming Language :: Python :: 3.9
Classifier: Programming Language :: Python :: 3.10
Classifier: Programming Language :: Python :: 3.11
Classifier: Programming Language :: Python :: 3.12
Classifier: Programming Language :: Rust
Classifier: Topic :: Software Development :: Libraries :: Python Modules
Summary: High-performance Rust implementation of validators - validate emails, URLs, IPs, and more
Keywords: validators,validation,email,url,performance,rust
Author: Rusputyn Contributors
Requires-Python: >=3.8
